simplidb/__init__.py
simplidb/simplidb.py
simplidb-0.2.3.dist-info/LICENSE
simplidb-0.2.3.dist-info/METADATA
simplidb-0.2.3.dist-info/WHEEL
simplidb-0.2.3.dist-info/top_level.txt
simplidb-0.2.3.dist-info/RECORD
