Metadata-Version: 2.1
Name: simplidb
Version: 0.2.3
Summary: A simple SQLite database wrapper (A package that provides a simplified interface for working with SQLite databases.)
Home-page: https://github.com/maulydev/SimpliDB
Author: Mauly dotDev
Author-email: mauly.dev@email.com
License: MIT
Project-URL: Bug Tracker, https://github.com/maulydev/SimpliDB/issues
Project-URL: Source Code, https://github.com/maulydev/SimpliDB
Keywords: SQLite,database,wrapper,simple,db
Classifier: Development Status :: 4 - Beta
Classifier: Intended Audience :: Developers
Classifier: License :: OSI Approved :: MIT License
Classifier: Programming Language :: Python :: 3
Classifier: Programming Language :: Python :: 3.7
Classifier: Programming Language :: Python :: 3.8
Classifier: Programming Language :: Python :: 3.9
Requires-Python: >=3.0
License-File: LICENSE
